{"qid": "Q1120700", "name": "Orson Bean", "match_basis": "qid", "ch_id": "38855", "ch_uri": "http://data.carnegiehall.org/names/38855", "birth": "1928", "death": "2020", "description": "American actor (1928–2020)", "abstract": "Orson Bean (born Dallas Frederick Burrows; July 22, 1928 – February 7, 2020) was an American film, television, and stage actor and comedian and a \"mainstay of Los Angeles’ small theater scene.\" He appeared frequently on several televised game shows from the 1960s through the 1980s and was a longtime panelist on the television game show T…", "wp_title": "Orson Bean", "image": "img/p/Q1120700.jpg", "is_interviewee": false, "lj_docs": 1, "lj_mentions": 1, "lj_node": "wd:Q1120700", "interviews": [], "concerts": [{"id": "21899", "date": "1954-11-10", "label": "Rally to Strengthen and Support the United Nations", "venue": "Main Hall", "roles": ["speaker"], "works": [{"t": "Selections (unspecified)", "c": null, "w": "104450"}]}, {"id": "34384", "date": "1957-05-11", "label": "Children's Asthma Research Institute and Hospital 3rd Annual Parade of Stars", "venue": "Main Hall", "roles": ["actor"], "works": [{"t": "Selections (unspecified)", "c": null, "w": "104450"}]}, {"id": "34374", "date": "1962-06-27", "label": "Tribute to Eleanor Roosevelt", "venue": "Main Hall", "roles": ["actor"], "works": [{"t": "Selections (unspecified)", "c": null, "w": "104450"}]}, {"id": "26915", "date": "1964-04-19", "label": "Festival of Music of Broadway", "venue": "Main Hall", "roles": ["actor"], "works": [{"t": "Selections (unspecified)", "c": null, "w": "104450"}]}, {"id": "301", "date": "1967-05-21", "label": "Benefit: Witlwyck School for Boys", "venue": "Main Hall", "roles": ["actor"], "works": [{"t": "Selections (unspecified)", "c": null, "w": "104450"}]}], "works_created": [], "quotes": [], "about_quotes": [{"speaker": "Jackie Cain and Roy Kral", "relation": "knows of", "confidence": 0.9, "evidence": "[INTERVIEWER] ...there were — people would come through like Orson Bean doing his comedy act... [INTERVIEWEE] Before anyone knew him.", "doc_title": "Jackie Cain and Roy Kral interviewed by Monk Rowe, New York City, New York, March 22, 1998", "collection": "hamilton", "url": "https://litsdigital.hamilton.edu/collections/object/jackie-cain-and-roy-kral-interviewed-monk-rowe-new-york-city-new-york-march-22"}]}