{"qid": "Q130798", "name": "Kendrick Lamar", "match_basis": "qid", "ch_id": "129502", "ch_uri": "http://data.carnegiehall.org/names/129502", "birth": "1987", "death": null, "description": "American rapper (born 1987)", "abstract": "Kendrick Lamar Duckworth (born June 17, 1987) is an American rapper and songwriter. Rooted in West Coast hip-hop, his music features conscious, introspective lyrics, with political criticism and social commentary concerning African-American culture.", "wp_title": "Kendrick Lamar", "image": "img/p/Q130798.jpg", "is_interviewee": false, "lj_docs": 1, "lj_mentions": 7, "lj_node": "wd:Q130798", "interviews": [], "concerts": [], "works_created": [], "quotes": [], "about_quotes": [{"speaker": "Robert Glasper", "relation": "collaborated with", "confidence": 1.0, "evidence": "Now tell us about your collaboration with Kendrick Lamar on “To Pimp a Butterfly.”", "doc_title": "Robert Glasper interviewed by Greg Thomas, Clinton, New York, February 20, 2016", "collection": "hamilton", "url": "https://litsdigital.hamilton.edu/collections/object/robert-glasper-interviewed-greg-thomas-clinton-new-york-february-20-2016"}]}