{"qid": "Q1603041", "name": "Terry Pollard", "match_basis": "qid", "ch_id": "43712", "ch_uri": "http://data.carnegiehall.org/names/43712", "birth": "1931", "death": "2009", "description": "jazz pianist prominent in the Detroit jazz scene of the 1940s and 1950s", "abstract": "Terry Pollard (August 15, 1931 – December 16, 2009) was an American jazz pianist and vibraphonist active in the Detroit jazz scene of the 1940s and 1950s. She has been described as a \"major player who was inexplicably overlooked.\"\nPollard began her career by collaborating with other Detroit musicians, such as Billy Mitchell (and Elvin Jo…", "wp_title": "Terry Pollard", "image": null, "is_interviewee": false, "lj_docs": 4, "lj_mentions": 9, "lj_node": "wd:Q1603041", "interviews": [], "concerts": [{"id": "29752", "date": "1957-02-16", "label": "Midnight Performance: Birdland Stars of '57", "venue": "Main Hall", "roles": ["piano"], "works": [{"t": "Selections (unspecified)", "c": null, "w": "104450"}]}, {"id": "43368", "date": "1957-02-17", "label": "Midnight Performance: Birdland Stars of '57", "venue": "Main Hall", "roles": ["piano"], "works": [{"t": "Selections (unspecified)", "c": null, "w": "104450"}]}], "works_created": [], "quotes": [], "about_quotes": [{"speaker": "Barry Harris", "relation": "collaborated with", "confidence": 0.9, "evidence": "Terry Pollard was part of our thing... I watched them... Terry Pollard played better than me", "doc_title": "Barry Harris — Smithsonian Jazz Oral History", "collection": "si", "url": "https://americanhistory.si.edu/sites/default/files/file-uploader/Barry-Harris-Transcription-2020.pdf"}]}