{"qid": "Q192185", "name": "Aaron Copland", "match_basis": "qid", "ch_id": "60485", "ch_uri": "http://data.carnegiehall.org/names/60485", "birth": "1900", "death": "1990", "description": "American composer, composition teacher, writer, and conductor (1900-1990)", "abstract": "Aaron Copland ( KOHP-lənd; November 14, 1900 – December 2, 1990) was an American composer, critic, writer, teacher, pianist, and conductor of his own and other American music. Copland was referred to by his peers and critics as the \"Dean of American Music\".", "wp_title": "Aaron Copland", "image": "img/p/Q192185.jpg", "is_interviewee": false, "lj_docs": 19, "lj_mentions": 28, "lj_node": "wd:Q192185", "interviews": [], "concerts": [{"id": "28869", "date": "1927-02-03", "label": "Boston Symphony Orchestra", "venue": "Main Hall", "roles": ["piano"], "works": [{"t": "Piano Concerto", "c": "Aaron Copland", "w": "9631"}]}, {"id": "7831", "date": "1927-04-10", "label": "George Antheil, Composer and Pianist", "venue": "Main Hall", "roles": ["piano"], "works": [{"t": "Ballet mécanique", "c": "George Antheil", "w": "57260"}]}, {"id": "16085", "date": "1927-10-12", "label": "Beethoven Symphony Orchestra", "venue": "Main Hall", "roles": ["piano"], "works": [{"t": "Cortège macabre", "c": "Aaron Copland", "w": "25020"}]}, {"id": "31963", "date": "1941-04-05", "label": "The Carnegie Hall Lectures: Panel Discussion", "venue": "Main Hall", "roles": ["speaker"], "works": [{"t": "Discussion", "c": "Unknown author of spoken text", "w": "48375"}]}, {"id": "6109", "date": "1948-01-03", "label": "Goldman Band: Tribute to Edwin Franko Goldman", "venue": "Main Hall", "roles": ["presenter"], "works": [{"t": "Presentation", "c": "Unknown author of spoken text", "w": "15777"}]}, {"id": "11710", "date": "1958-01-30", "label": "New York Philharmonic", "venue": "Main Hall", "roles": ["conductor"], "works": [{"t": "Symphony No. 3", "c": "Aaron Copland", "w": "29007"}]}, {"id": "11711", "date": "1958-01-31", "label": "New York Philharmonic", "venue": "Main Hall", "roles": ["conductor"], "works": [{"t": "An Outdoor Overture", "c": "Aaron Copland", "w": "23838"}, {"t": "Symphony No. 3", "c": "Aaron Copland", "w": "29007"}]}, {"id": "16062", "date": "1958-02-01", "label": "New York Philharmonic Young People's Concert", "venue": "Main Hall", "roles": ["conductor"], "works": [{"t": "Symphony No. 3: Excerpts (unspecified)", "c": "Aaron Copland", "w": "2740"}]}, {"id": "2733", "date": "1959-11-21", "label": "Boston Symphony Orchestra", "venue": "Main Hall", "roles": ["conductor"], "works": [{"t": "The Tender Land: Suite", "c": "Aaron Copland", "w": "58469"}]}, {"id": "34874", "date": "1960-02-08", "label": "Ned Rorem and William Flanagan: Music for the Voice by American Composers", "venue": "Carnegie Recital Hall", "roles": ["piano"], "works": [{"t": "12 Poems of Emily Dickinson", "c": "Aaron Copland", "w": "39532"}, {"t": "As It Fell Upon a Day", "c": "Aaron Copland", "w": "20951"}]}, {"id": "32434", "date": "1960-11-12", "label": "New York Philharmonic Young People's Concert: Aaron Copland's 60th Birthday Party", "venue": "Main Hall", "roles": ["conductor"], "works": [{"t": "El salón México", "c": "Aaron Copland", "w": "5492"}, {"t": "Rodeo: Buckaroo Holiday", "c": "Aaron Copland", "w": "1047"}]}, {"id": "19549", "date": "1961-02-13", "label": "New York Philharmonic", "venue": "Main Hall", "roles": ["conductor"], "works": [{"t": "Candide: Overture", "c": "Leonard Bernstein", "w": "38576"}]}, {"id": "6957", "date": "1968-05-24", "label": "Composers and Musicians for Peace: A Tribute to Martin Luther King Jr.", "venue": "Main Hall", "roles": ["conductor"], "works": [{"t": "The Tender Land: Stomp Your Foot", "c": "Aaron Copland", "w": "34826"}, {"t": "The Tender Land: The Promise of Living", "c": "Aaron Copland", "w": "47116"}]}, {"id": "25074", "date": "1975-12-15", "label": "Naumberg Foundation 50th Anniversary Celebration", "venue": "Main Hall", "roles": ["speaker"], "works": [{"t": "Address", "c": "Unknown author of spoken text", "w": "4930"}]}, {"id": "8170", "date": "1980-11-09", "label": "American Symphony Orchestra: Aaron Copland 80th Birthday Celebration", "venue": "Main Hall", "roles": ["conductor", "narrator", "speaker"], "works": [{"t": "Symphony No. 2, \"Short Symphony\"", "c": "Aaron Copland", "w": "29008"}, {"t": "12 Poems of Emily Dickinson: 4. The world feels dusty", "c": "Aaron Copland", "w": "19340"}, {"t": "12 Poems of Emily Dickinson: 12. The Chariot", "c": "Aaron Copland", "w": "52025"}, {"t": "Lincoln Portrait", "c": "Aaron Copland", "w": "26277"}, {"t": "12 Poems of Emily Dickinson: 1. Nature, the gentlest mother", "c": "Aaron Copland", "w": "34853"}, {"t": "12 Poems of Emily Dickinson: 11. Going to Heaven!", "c": "Aaron Copland", "w": "4587"}, {"t": "12 Poems of Emily Dickinson: 2. There came a wind like a bugle", "c": "Aaron Copland", "w": "31580"}, {"t": "12 Poems of Emily Dickinson: 5. Heart, we will forget him!", "c": "Aaron Copland", "w": "1985"}, {"t": "12 Poems of Emily Dickinson: 6. Dear March, come in!", "c": "Aaron Copland", "w": "60009"}, {"t": "12 Poems of Emily Dickinson: 7. Sleep is supposed to be", "c": "Aaron Copland", "w": "29821"}, {"t": "Remarks", "c": "Unknown author of spoken text", "w": "1315"}, {"t": "The Tender Land: Suite", "c": "Aaron Copland", "w": "58469"}]}], "works_created": [{"t": "Duo for Flute and Piano", "w": "48693"}, {"t": "Old American Songs: Selections (unspecified)", "w": "111426"}, {"t": "Passacaglia", "w": "43876"}, {"t": "The Second Hurricane: Act II. Queenie's Song", "w": "47741"}, {"t": "Rodeo: Hoedown", "w": "5495"}, {"t": "Appalachian Spring", "w": "49635"}, {"t": "Hoe-Down from \"Rodeo\"", "w": "101350"}, {"t": "Selection for piano (unspecified)", "w": "116916"}, {"t": "The Tender Land: The Promise of Living", "w": "111792"}, {"t": "Old American Songs, Set 1: Simple Gifts", "w": "87175"}, {"t": "Three Latin American Sketches", "w": "16917"}, {"t": "Rodeo: Selection (unspecified)", "w": "69074"}, {"t": "Old American Songs: Selection (unspecified)", "w": "122770"}, {"t": "Piano Sonata: 2. Vivace", "w": "52578"}, {"t": "12 Poems of Emily Dickinson", "w": "39532"}, {"t": "Danzón cubano", "w": "43177"}, {"t": "Duo for Flute and Piano: 3. Lively, with bounce", "w": "31511"}, {"t": "John Henry", "w": "8954"}, {"t": "Our Town: 3 Excerpts for Piano", "w": "9646"}, {"t": "The Tender Land: Suite", "w": "58469"}, {"t": "Simple Gifts", "w": "111338"}, {"t": "An Immorality", "w": "13161"}, {"t": "Our Town: Suite", "w": "77831"}, {"t": "The Tender Land: Laurie's Song", "w": "32142"}, {"t": "Down a Country Lane", "w": "93328"}, {"t": "Rodeo: Buckaroo Holiday", "w": "114501"}, {"t": "12 Poems of Emily Dickinson: 9. I felt a funeral in my brain", "w": "54697"}, {"t": "Symphonic Ode (Revised version)", "w": "88913"}, {"t": "12 Poems of Emily Dickinson: 12. The Chariot", "w": "52025"}, {"t": "The Red Pony: Suite", "w": "18520"}, {"t": "Billy the Kid: Waltz", "w": "9418"}, {"t": "Rodeo: Hoedown", "w": "118169"}, {"t": "Selection (unspecified)", "w": "10446"}, {"t": "12 Poems of Emily Dickinson: 2. There came a wind like a bugle", "w": "31580"}, {"t": "Music for the Theatre: Excerpts (unspecified)", "w": "13956"}, {"t": "Old American Songs, Set 2: 4. At the River", "w": "49775"}, {"t": "Statements", "w": "33271"}, {"t": "Rodeo: Buckaroo Holiday", "w": "1047"}, {"t": "Petit Portrait", "w": "125932"}, {"t": "The Tender Land: The Promise of Living", "w": "47116"}], "quotes": [], "about_quotes": [{"speaker": "Ted Piltzecker", "relation": "knows of", "confidence": 1.0, "evidence": "I happen to teach melody writing... I was surprised when I first read that Aaron Copland, who wrote some really incredible melodies, and he said...", "doc_title": "Ted Piltzecker interviewed by Monk Rowe, Clinton, New York, October 10, 2019", "collection": "hamilton", "url": "https://litsdigital.hamilton.edu/collections/object/ted-piltzecker-interviewed-monk-rowe-clinton-new-york-october-10-2019"}, {"speaker": "Al Chez", "relation": "knows of", "confidence": 1.0, "evidence": "Alec Baldwin likes classical music. Okay let’s play “Simple Gifts” by Aaron Copland.", "doc_title": "Al Chez interviewed by Monk Rowe, New Hartford, New York, February 13, 2019", "collection": "hamilton", "url": "https://litsdigital.hamilton.edu/collections/object/al-chez-interviewed-monk-rowe-new-hartford-new-york-february-13-2019"}, {"speaker": "Mike Longo", "relation": "knows of", "confidence": 1.0, "evidence": "Look man, Aaron Copland said, “The art of classical music is the art of melody.”", "doc_title": "Mike Longo interviewed by Monk Rowe, New York City, New York, January 13, 2019", "collection": "hamilton", "url": "https://litsdigital.hamilton.edu/collections/object/mike-longo-interviewed-monk-rowe-new-york-city-new-york-january-13-2019"}, {"speaker": "John Heard", "relation": "knows of", "confidence": 0.9, "evidence": "The interviewee only responds to the interviewer's mention of Aaron Copland with agreement ('Yeah, that’s right') and pivots to discussing Duke Ellington. There is no evidence of a personal relationship, meeting, or collaboration between John Heard and Aaron Copland.", "doc_title": "John Heard interviewed by Monk Rowe and Michael Woods, Scottsdale, Arizona, March 4, 1995", "collection": "hamilton", "url": "https://litsdigital.hamilton.edu/collections/object/john-heard-interviewed-monk-rowe-and-michael-woods-scottsdale-arizona-march-4"}, {"speaker": "Akiyoshi Toshiko", "relation": "knows of", "confidence": 0.9, "evidence": "[INTERVIEWER] I said Aaron, Aaron Copland. [INTERVIEWEE] Oh, yes, right. That‟s what they said and it was … but he, he wanted to, so…. But his November Steps is the classic one and he liked to use the biwa", "doc_title": "Akiyoshi Toshiko — Smithsonian Jazz Oral History", "collection": "si", "url": "https://amhistory.si.edu/jazz/Akiyoshi-Toshiko/Toshiko_Akiyoshi_Transcript.pdf"}, {"speaker": "Alan Raph", "relation": "collaborated with", "confidence": 0.9, "evidence": "I worked with Aaron not much, with a little orchestra society... Aaron came into conduct his theater music and I think that’s the only time I ever worked for him, or with him.", "doc_title": "Alan Raph interviewed by Monk Rowe, Danbury, Connecticut, November 20, 2001", "collection": "hamilton", "url": "https://litsdigital.hamilton.edu/collections/object/alan-raph-interviewed-monk-rowe-danbury-connecticut-november-20-2001"}]}