{"qid": "Q19624438", "name": "Jack Six", "match_basis": "qid", "ch_id": "7582", "ch_uri": "http://data.carnegiehall.org/names/7582", "birth": "1930", "death": "2015", "description": "American jazz musician", "abstract": "Jack Six (July 26, 1930 – March 14, 2015) was an American jazz double-bassist and composer. Six was born in Danville, Illinois, and initially learned trumpet as a teenager before switching to bass.", "wp_title": "Jack Six", "image": null, "is_interviewee": false, "lj_docs": 4, "lj_mentions": 10, "lj_node": "wd:Q19624438", "interviews": [], "concerts": [{"id": "70305", "date": "1961-09-25", "label": "Music of Paul Knopf", "venue": "Carnegie Recital Hall", "roles": ["double_bass"], "works": [{"t": "Mats and Rice", "c": "Paul Knopf", "w": "114331"}, {"t": "Porgies and Bass", "c": "Paul Knopf", "w": "114332"}, {"t": "Bed, Broad 'n' Bread", "c": "Paul Knopf", "w": "114330"}, {"t": "Eddy Poose", "c": "Paul Knopf", "w": "114329"}]}, {"id": "75934", "date": "1967-01-23", "label": "Jack Reilly, Piano", "venue": "Carnegie Recital Hall", "roles": ["double_bass"], "works": [{"t": "Half Step", "c": "Jack Reilly", "w": "119820"}, {"t": "Lanot-1B Suite No. 1", "c": "Jack Reilly", "w": "119823"}, {"t": "Psalms", "c": "Jack Reilly", "w": "119824"}, {"t": "Suite for Eebee", "c": "Jack Reilly", "w": "119822"}, {"t": "Blue Sean Green", "c": "Jack Reilly", "w": "119819"}, {"t": "Sonata for Piano, Bass, and Drums in D Minor", "c": "Jack Reilly", "w": "119821"}]}, {"id": "15867", "date": "1972-03-05", "label": "Dave Brubeck Quartet/ Gerry Mulligan/ Paul Desmond/ Darius Brubeck Ensemble", "venue": "Main Hall", "roles": ["double_bass"], "works": [{"t": "Selections (unspecified)", "c": null, "w": "104450"}]}, {"id": "7495", "date": "1975-11-02", "label": "Superstars II", "venue": "Main Hall", "roles": ["double_bass"], "works": [{"t": "Selections (unspecified)", "c": null, "w": "104450"}]}, {"id": "28254", "date": "1981-06-29", "label": "Kool Jazz Festival: Musicians for Each Other", "venue": "Main Hall", "roles": ["double_bass"], "works": [{"t": "St. Louis Blues", "c": "W. C. Handy", "w": "45163"}]}, {"id": "19859", "date": "1989-06-27", "label": "JVC Jazz Festival: Jazz and The American Song", "venue": "Main Hall", "roles": ["double_bass"], "works": [{"t": "Selections (unspecified)", "c": null, "w": "104450"}]}, {"id": "5341", "date": "1990-02-18", "label": "Brown University Chorus and Orchestra", "venue": "Main Hall", "roles": ["double_bass"], "works": [{"t": "In Your Own Sweet Way", "c": "Dave Brubeck", "w": "26458"}, {"t": "Selections (unspecified)", "c": null, "w": "104450"}, {"t": "Mass: The Peace of Jerusalem", "c": "Dave Brubeck", "w": "36792"}, {"t": "Blue Rondo à la Turk", "c": "Dave Brubeck", "w": "55244"}, {"t": "The Light in the Wilderness: The Kingdom", "c": "Dave Brubeck", "w": "54084"}, {"t": "The Gates of Justice: Out of the Way of the People", "c": "Dave Brubeck", "w": "12775"}]}, {"id": "15824", "date": "1993-12-02", "label": "Salute to Oscar Peterson", "venue": "Main Hall", "roles": ["double_bass"], "works": [{"t": "Selections (unspecified)", "c": null, "w": "104450"}]}, {"id": "11379", "date": "1997-11-17", "label": "Time for Peace Awards Ceremony and Concert", "venue": "Isaac Stern Auditorium / Ronald O. Perelman Stage", "roles": ["double_bass"], "works": [{"t": "Selections (unspecified)", "c": null, "w": "104450"}]}], "works_created": [], "quotes": [], "about_quotes": [{"speaker": "Dave Brubeck", "relation": "knows of", "confidence": 0.9, "evidence": "The name 'Jack Six' does not appear in the transcript. The interviewer mentions 'Jack Sheedy', 'Jack Weeks', and 'Jack Fina', but the interviewee (Dave Brubeck) does not mention Jack Six or describe any relationship with him.", "doc_title": "Dave Brubeck — Smithsonian Jazz Oral History", "collection": "si", "url": "https://americanhistory.si.edu/sites/default/files/file-uploader/Dave-Brubeck-Transcription-2020.pdf"}, {"speaker": "Dave Frishberg", "relation": "has met", "confidence": 0.9, "evidence": "met a couple of musicians, one of them was a guy I’ve known ever since, a bass player by the name of Jack Six.", "doc_title": "Dave Frishberg interviewed by Monk Rowe, Clearwater Beach, Florida, March 16, 2001", "collection": "hamilton", "url": "https://litsdigital.hamilton.edu/collections/object/dave-frishberg-interviewed-monk-rowe-clearwater-beach-florida-march-16-2001"}, {"speaker": "Brubeck", "relation": "collaborated with", "confidence": 0.9, "evidence": "Jack Six and those guys made some wonderful records together.", "doc_title": "Brubeck interviewed by Monk Rowe, 2022", "collection": "hamilton", "url": "https://litsdigital.hamilton.edu/collections/fillius-jazz-archive"}, {"speaker": "Jay McShann", "relation": "in music group with", "confidence": 0.9, "evidence": "Jack Six, bass, and a man with Duke, tenor man, Harold Ashby.", "doc_title": "52193_Jay McShann oral history interview", "collection": "rutgers", "url": "https://rucore.libraries.rutgers.edu/rutgers-lib/52193/"}]}