{"qid": "Q2604332", "name": "Michael Colgrass", "match_basis": "qid", "ch_id": "130079", "ch_uri": "http://data.carnegiehall.org/names/130079", "birth": "1932", "death": "2019", "description": "Canadian musician and composer (1932-2019)", "abstract": "Michael Charles Colgrass (April 22, 1932 – July 2, 2019) was an American and Canadian musician, composer, and educator. He was an associate composer of the Canadian Music Centre.", "wp_title": "Michael Colgrass", "image": null, "is_interviewee": false, "lj_docs": 1, "lj_mentions": 1, "lj_node": "wd:Q2604332", "interviews": [], "concerts": [{"id": "70524", "date": "1961-11-21", "label": "Concert by the National Association for American Composers and Conductors", "venue": "Carnegie Recital Hall", "roles": ["percussion"], "works": [{"t": "Fantasy-Variations", "c": "Michael Colgrass", "w": "114636"}]}, {"id": "72367", "date": "1962-10-27", "label": "Bernard Zaslav, Viola, and Naomi Zaslav, Piano", "venue": "Carnegie Recital Hall", "roles": ["drums"], "works": [{"t": "Variations for 4 Drums and Viola", "c": "Michael Colgrass", "w": "116212"}]}], "works_created": [{"t": "Variations for 4 Drums and Viola", "w": "116212"}, {"t": "Bali", "w": "78885"}, {"t": "Metamusic", "w": "75224"}, {"t": "Fantasy-Variations", "w": "114636"}, {"t": "The Beethoven Machine", "w": "99966"}, {"t": "Memento", "w": "50807"}, {"t": "The Schubert Birds", "w": "53227"}, {"t": "Déjà vu", "w": "22150"}, {"t": "Mysterious Village", "w": "79382"}, {"t": "Old Churches", "w": "96574"}, {"t": "As Quiet As", "w": "27556"}, {"t": "Concertmasters", "w": "32447"}, {"t": "Light Spirit", "w": "6888"}, {"t": "Delta", "w": "43126"}, {"t": "Wind Quintet", "w": "73648"}, {"t": "Variations for 4 Drums and Viola: Selections (unspecified)", "w": "35484"}], "quotes": [], "about_quotes": [{"speaker": "Teddy Wilson", "relation": "knows of", "confidence": 1.0, "evidence": "The mention of Michael Colgrass is made by [MR. WILSON, JR.], not the interviewee [Teddy Wilson]. The interviewee does not speak about Colgrass.", "doc_title": "66600_Teddy Wilson oral history interview", "collection": "rutgers", "url": "https://rucore.libraries.rutgers.edu/rutgers-lib/66600/"}]}