{"qid": "Q345446", "name": "Ernesto Lecuona", "match_basis": "qid", "ch_id": "26787", "ch_uri": "http://data.carnegiehall.org/names/26787", "birth": "1896", "death": "1963", "description": "Cuban composer (1896-1963)", "abstract": "Ernesto Lecuona y Casado (Spanish pronunciation: [eɾˈnesto leˈkwona]; August 7, 1896 – November 29, 1963) was a Cuban composer and pianist, many of whose works have become standards of the Latin, jazz and classical repertoires. His over 600 compositions include songs and zarzuelas as well as pieces for piano and symphonic orchestra.", "wp_title": "Ernesto Lecuona", "image": "img/p/Q345446.jpg", "is_interviewee": false, "lj_docs": 2, "lj_mentions": 2, "lj_node": "wd:Q345446", "interviews": [], "concerts": [{"id": "23548", "date": "1943-10-10", "label": "Ernesto Lecuona and his Symphony Orchestra", "venue": "Main Hall", "roles": ["piano"], "works": [{"t": "Malagueña", "c": "Ernesto Lecuona", "w": "18559"}, {"t": "Siempre en mi corazón (Always in my heart)", "c": "Ernesto Lecuona", "w": "55298"}, {"t": "Por que te vas?", "c": "Ernesto Lecuona", "w": "41985"}, {"t": "Aragón", "c": "Ernesto Lecuona", "w": "31493"}, {"t": "Danzas afro-cubanas: Danza lucumí", "c": "Ernesto Lecuona", "w": "41990"}, {"t": "Lola está de Fiesta", "c": "Ernesto Lecuona", "w": "32212"}]}, {"id": "33883", "date": "1945-11-17", "label": "Benefit: Common Council for American Unity", "venue": "Main Hall", "roles": ["piano"], "works": [{"t": "Selections (unspecified)", "c": null, "w": "104450"}]}, {"id": "22242", "date": "1946-05-11", "label": "Carnegie Pop Concert", "venue": "Main Hall", "roles": ["piano"], "works": [{"t": "Selections (unspecified)", "c": null, "w": "104450"}]}, {"id": "21600", "date": "1948-11-20", "label": "Ernesto Lecuona and Others", "venue": "Main Hall", "roles": ["piano"], "works": [{"t": "Quiéreme mucho", "c": "Gonzalo Roig", "w": "46215"}, {"t": "Guajira", "c": "Oscar Calle", "w": "31035"}, {"t": "Noche azul", "c": "Ernesto Lecuona", "w": "31036"}, {"t": "Danzas afro-cubanas: Danza lucumí", "c": "Ernesto Lecuona", "w": "41990"}, {"t": "Por que te vas?", "c": "Ernesto Lecuona", "w": "41985"}, {"t": "Malagueña", "c": "Ernesto Lecuona", "w": "18559"}, {"t": "Ahí viene el chino", "c": "Ernesto Lecuona", "w": "41773"}, {"t": "Tú (Habanera)", "c": "Eduardo Sánchez de Fuentes", "w": "43137"}, {"t": "María la O", "c": "Ernesto Lecuona", "w": "6721"}]}], "works_created": [{"t": "María la O: Romanza de María", "w": "118126"}, {"t": "Rapsodia negra", "w": "35995"}, {"t": "En tres por cuatro", "w": "13018"}, {"t": "Tribute à Ernesto Lecuona", "w": "11950"}, {"t": "Donna Maria", "w": "69263"}, {"t": "Ella y yo", "w": "37124"}, {"t": "María la O", "w": "6721"}, {"t": "Por eso te quiero", "w": "119903"}, {"t": "El dulcero", "w": "99279"}, {"t": "Mi vida", "w": "8612"}, {"t": "Malagueña", "w": "125912"}, {"t": "Danzas afro-cubanas: Danza negra", "w": "104029"}, {"t": "Aragón", "w": "31493"}, {"t": "El cafetal: Cancion de Africa", "w": "61014"}, {"t": "Andalucía", "w": "1900"}, {"t": "No hay perdon", "w": "57239"}, {"t": "Una rosa blanca", "w": "22078"}, {"t": "Canción del amor triste", "w": "81171"}, {"t": "Ahí viene el chino", "w": "41773"}, {"t": "Arabesque", "w": "4173"}, {"t": "Noche azul", "w": "31036"}, {"t": "Granada", "w": "32702"}, {"t": "Nineteenth Century Cuban Dances: La Mulata", "w": "48727"}, {"t": "Danzas afro-cubanas: ¡Y la negra bailaba!", "w": "33488"}, {"t": "Yo te quiero siempre", "w": "94923"}, {"t": "Malagueña", "w": "88848"}, {"t": "Malagueña", "w": "108542"}, {"t": "War Melodies", "w": "48946"}, {"t": "Danzas afro-cubanas: Danza negra", "w": "29415"}, {"t": "Bolero Español", "w": "80260"}, {"t": "Danzas afro-cubanas: Danza lucumí", "w": "41990"}, {"t": "Song (unspecified)", "w": "68430"}, {"t": "Rosa la china: Yo viví soñando", "w": "84393"}, {"t": "La primera en la frente", "w": "20121"}, {"t": "Song of the Sad Love", "w": "11832"}, {"t": "Por que te vas?", "w": "41985"}, {"t": "Siboney", "w": "3129"}, {"t": "San Francisco el Grande", "w": "62668"}, {"t": "Suite Espagnol", "w": "11831"}, {"t": "I'm Living from Kiss to Kiss", "w": "33495"}], "quotes": [], "about_quotes": [{"speaker": "Paquito D'Rivera", "relation": "knows of", "confidence": 0.9, "evidence": "Ernesto Lecuona was white and was the representative of the Afro-Cuban composers was a white guy, was Ernesto Lecuona and nobody denied that.", "doc_title": "Paquito D'Rivera — Smithsonian Jazz Oral History", "collection": "si", "url": "https://amhistory.si.edu/jazz/Drivera-Paquito/D'Rivera_Paquito_%20Interview_Transcription.pdf"}]}