{"qid": "Q44641", "name": "Wendy Carlos", "match_basis": "qid", "ch_id": "1021083", "ch_uri": "http://data.carnegiehall.org/names/1021083", "birth": "1939", "death": null, "description": "American composer and electronic musician (born 1939)", "abstract": "Wendy Carlos (born Walter Carlos, November 14, 1939) is an American musician and composer known for electronic music and film scores. Born and raised in Rhode Island, Carlos studied physics and music at Brown University before moving to New York City in 1962 to study music composition at Columbia University.", "wp_title": "Wendy Carlos", "image": "img/p/Q44641.jpg", "is_interviewee": false, "lj_docs": 1, "lj_mentions": 1, "lj_node": "wd:Q44641", "interviews": [], "concerts": [], "works_created": [], "quotes": [], "about_quotes": [{"speaker": "Quincy Jones", "relation": "knows of", "confidence": 0.9, "evidence": "Before Walter Carlos or anybody – Wendy Carlos. You know about that, don’t you?", "doc_title": "Quincy Jones — Smithsonian Jazz Oral History", "collection": "si", "url": "https://amhistory.si.edu/jazz/Jones-Quincy/Jones_Quincy_Transcript.pdf"}]}