{"qid": "Q7231617", "name": "Porter Grainger", "match_basis": "qid", "ch_id": "1013701", "ch_uri": "http://data.carnegiehall.org/names/1013701", "birth": "1891", "death": "1955", "description": "American musician (1891–1955)", "abstract": "Porter Grainger (né Granger; October 22, 1891 − October 30, 1948) was an African American pianist, songwriter, playwright, and music publisher.", "wp_title": "Porter Grainger", "image": null, "is_interviewee": false, "lj_docs": 2, "lj_mentions": 4, "lj_node": "wd:Q7231617", "interviews": [], "concerts": [], "works_created": [{"t": "Ain't Nobody's Business", "w": "44215"}], "quotes": [], "about_quotes": [{"speaker": "Alberta Hunter", "relation": "collaborated with", "confidence": 0.9, "evidence": "Business -- that's Porter Grainger's song. Porter Grainger wrote that. And I introduced it.", "doc_title": "68436_Alberta Hunter oral history interview", "collection": "rutgers", "url": "https://rucore.libraries.rutgers.edu/rutgers-lib/68436/"}]}