{"qid": "Q7705337", "name": "Teruo Nakamura", "match_basis": "qid", "ch_id": "8049", "ch_uri": "http://data.carnegiehall.org/names/8049", "birth": "1942", "death": null, "description": "Japanese jazz bassist and producer", "abstract": "Teruo Nakamura (中村 照夫, Nakamura Teruo; born 3 March 3, 1942) is a Japanese jazz bassist and record producer.", "wp_title": "Teruo Nakamura (musician)", "image": null, "is_interviewee": false, "lj_docs": 1, "lj_mentions": 1, "lj_node": "wd:Q7705337", "interviews": [], "concerts": [{"id": "10749", "date": "1975-07-02", "label": "Newport Jazz Festival: Stanley Turrentine, John Klemmer, and Hampton Hawes", "venue": "Main Hall", "roles": ["double_bass"], "works": [{"t": "Sugar", "c": "Stanley Turrentine", "w": "73543"}, {"t": "Naked as the Day I Was Born", "c": "Billy Page", "w": "107077"}, {"t": "I'm in Love", "c": "Bobby Womack", "w": "107078"}, {"t": "Don't Mess With Mister T.", "c": "Marvin Gaye", "w": "107079"}, {"t": "I Know It's You", "c": "Leon Ware", "w": "107076"}, {"t": "Pieces of Dreams", "c": "Michel Legrand", "w": "54274"}]}], "works_created": [], "quotes": [], "about_quotes": []}