{"qid": "Q888675", "name": "Bobby Short", "match_basis": "qid", "ch_id": "34676", "ch_uri": "http://data.carnegiehall.org/names/34676", "birth": "1924", "death": "2005", "description": "American singer and pianist (1924–2005)", "abstract": "Robert Waltrip Short (September 15, 1924 – March 21, 2005) was an American cabaret singer and pianist who interpreted songs by popular composers from the first half of the 20th century such as Rodgers and Hart, Cole Porter, Jerome Kern, Harold Arlen, Richard A. Whiting, Vernon Duke, Noël Coward and George and Ira Gershwin.", "wp_title": "Bobby Short", "image": "img/p/Q888675.jpg", "is_interviewee": false, "lj_docs": 24, "lj_mentions": 51, "lj_node": "wd:Q888675", "interviews": [], "concerts": [{"id": "2435", "date": "1962-10-05", "label": "Bobby Short, Singer and PIanist", "venue": "Main Hall", "roles": ["piano", "vocalist", "whistler"], "works": [{"t": "Nashville Nightingale", "c": "George Gershwin", "w": "104751"}, {"t": "Lydia, the Tattooed Lady", "c": "Harold Arlen", "w": "100558"}, {"t": "I'm a Dreamer (Aren't We All)", "c": "Ray Henderson", "w": "116193"}, {"t": "A to Z: And Her Mother Came Too!", "c": "Ivor Novello", "w": "60469"}, {"t": "If I Had a Talking Picture of You", "c": "Ray Henderson", "w": "116192"}, {"t": "Selections (unspecified)", "c": null, "w": "104450"}, {"t": "Fifty Million Frenchmen: I Worship You", "c": "Cole Porter", "w": "82380"}, {"t": "Fifty Million Frenchmen: You Do Something to Me", "c": "Cole Porter", "w": "40351"}]}, {"id": "34125", "date": "1972-07-08", "label": "Newport Jazz Festival: Duke Ellington and His Orchestra and the Terumasa Hino Sextet", "venue": "Main Hall", "roles": ["piano", "vocalist"], "works": [{"t": "I Got It Bad (and That Ain't Good)", "c": "Duke Ellington", "w": "34237"}, {"t": "Sophisticated Ladies: It Don't Mean a Thing", "c": "Duke Ellington", "w": "11677"}, {"t": "Me and You", "c": "Duke Ellington", "w": "105242"}, {"t": "You Can Count on Me", "c": "Robert Maxwell", "w": "105243"}]}, {"id": "10391", "date": "1977-03-06", "label": "Mabel Mercer and Bobby Short", "venue": "Main Hall", "roles": ["piano", "tenor"], "works": [{"t": "Selections (unspecified)", "c": null, "w": "104450"}]}, {"id": "12294", "date": "1978-10-12", "label": "By Ira...By George: Gala Concert of Songs and Music by the Gershwins", "venue": "Main Hall", "roles": ["tenor"], "works": [{"t": "Our Nell: Innocent Ingenue Baby", "c": "George Gershwin", "w": "72470"}, {"t": "I must be home by twelve o’clock", "c": "George Gershwin", "w": "72472"}, {"t": "Pardon My English: Isn’t It a Pity?", "c": "George Gershwin", "w": "56923"}]}, {"id": "31477", "date": "1981-03-06", "label": "Kool Super Nights: A Joyous Salute to W.C. Handy", "venue": "Main Hall", "roles": ["tenor"], "works": [{"t": "Oh Say Wouldn't It Be a Dream", "c": "Joe Jordan", "w": "56301"}, {"t": "The Unbeliever", "c": "Bert Williams", "w": "4889"}, {"t": "Carry Me Back to Old Virginny", "c": "James A. Bland", "w": "2604"}, {"t": "My Old Virginia Home", "c": "Charles T. Frey", "w": "32389"}, {"t": "Under the Bamboo Tree", "c": "Bob Cole", "w": "18925"}, {"t": "I Wish I Could Shimmy Like My Sister Kate", "c": "Armand J. Piron", "w": "49747"}, {"t": "Oh, Dem Golden Slippers", "c": "James A. Bland", "w": "33196"}, {"t": "Witness", "c": "Spiritual", "w": "23087"}]}, {"id": "34558", "date": "1984-06-25", "label": "Kool Jazz Festival: An Evening of the Music of Harold Arlen", "venue": "Main Hall", "roles": ["piano"], "works": [{"t": "Selections (unspecified)", "c": null, "w": "104450"}]}, {"id": "27522", "date": "1985-06-27", "label": "Kool Jazz Festival: Stormy Weather: A Salute to Ethel Waters", "venue": "Main Hall", "roles": ["piano", "tenor"], "works": [{"t": "Selections (unspecified)", "c": null, "w": "104450"}]}, {"id": "30238", "date": "1985-11-08", "label": "Osborne 100th Anniversary Concert and Auction", "venue": "Carnegie Recital Hall", "roles": ["piano"], "works": [{"t": "Selections (unspecified)", "c": null, "w": "104450"}]}, {"id": "21589", "date": "1986-03-21", "label": "The New York Pops", "venue": "Main Hall", "roles": ["piano"], "works": [{"t": "Selections (unspecified)", "c": null, "w": "104450"}]}, {"id": "1672", "date": "1987-05-08", "label": "The New York Pops", "venue": "Main Hall", "roles": ["piano"], "works": [{"t": "You Never Know: At Long Last Love", "c": "Cole Porter", "w": "37752"}, {"t": "Body and Soul", "c": "Johnny Green", "w": "18064"}, {"t": "Girl Crazy: But Not for Me", "c": "George Gershwin", "w": "10220"}, {"t": "Jubilee: Just One of Those Things", "c": "Cole Porter", "w": "51419"}, {"t": "Selections (unspecified)", "c": null, "w": "104450"}, {"t": "Gay Divorce: Night and Day", "c": "Cole Porter", "w": "16101"}]}, {"id": "13453", "date": "1987-05-09", "label": "The New York Pops", "venue": "Main Hall", "roles": ["piano"], "works": [{"t": "Jubilee: Just One of Those Things", "c": "Cole Porter", "w": "51419"}, {"t": "Gay Divorce: Night and Day", "c": "Cole Porter", "w": "16101"}, {"t": "You Never Know: At Long Last Love", "c": "Cole Porter", "w": "37752"}, {"t": "Girl Crazy: But Not for Me", "c": "George Gershwin", "w": "10220"}, {"t": "Selections (unspecified)", "c": null, "w": "104450"}, {"t": "Body and Soul", "c": "Johnny Green", "w": "18064"}]}, {"id": "19859", "date": "1989-06-27", "label": "JVC Jazz Festival: Jazz and The American Song", "venue": "Main Hall", "roles": ["host"], "works": [{"t": "Selections (unspecified)", "c": null, "w": "104450"}]}, {"id": "30349", "date": "1990-05-16", "label": "An Evening of Fashion and Music to Benefit Carnegie Hall", "venue": "Main Hall", "roles": ["piano"], "works": [{"t": "Selections (unspecified)", "c": null, "w": "104450"}]}, {"id": "6673", "date": "1991-01-11", "label": "The New York Pops", "venue": "Main Hall", "roles": ["piano"], "works": [{"t": "Selections (unspecified)", "c": "George Gershwin", "w": "105187"}]}, {"id": "12334", "date": "1991-06-09", "label": "Cole Porter 100th Birthday Celebration", "venue": "Main Hall", "roles": ["piano"], "works": [{"t": "You Never Know: At Long Last Love", "c": "Cole Porter", "w": "37752"}, {"t": "Anything Goes: Anything Goes", "c": "Cole Porter", "w": "22916"}]}, {"id": "19425", "date": "1991-06-23", "label": "JVC Jazz Festival: Bobby Short", "venue": "Main Hall", "roles": ["piano", "tenor"], "works": [{"t": "Selections (unspecified)", "c": null, "w": "104450"}]}, {"id": "35343", "date": "1998-04-06", "label": "From Harlem to Hollywood: A Tribute to the Nicholas Brothers \"Tap Legends\"", "venue": "Isaac Stern Auditorium / Ronald O. Perelman Stage", "roles": ["piano"], "works": [{"t": "Selections (unspecified)", "c": null, "w": "104450"}]}, {"id": "22743", "date": "1999-11-05", "label": "The New York Pops", "venue": "Isaac Stern Auditorium / Ronald O. Perelman Stage", "roles": ["piano"], "works": [{"t": "Guess Who's In Town", "c": "J. C. Johnson", "w": "39681"}, {"t": "Take Love Easy", "c": "Duke Ellington", "w": "16041"}, {"t": "Sophisticated Lady", "c": "Duke Ellington", "w": "54118"}, {"t": "In a Mellotone", "c": "Duke Ellington", "w": "50719"}, {"t": "In The Dark", "c": "[first name unknown] Hill", "w": "38159"}, {"t": "You Never Know: At Long Last Love", "c": "Cole Porter", "w": "37752"}, {"t": "Jubilee: Just One of Those Things", "c": "Cole Porter", "w": "51419"}, {"t": "Street of Dreams", "c": "Victor Young", "w": "6441"}]}, {"id": "32165", "date": "1999-12-01", "label": "Noel Coward Celebration", "venue": "Isaac Stern Auditorium / Ronald O. Perelman Stage", "roles": ["piano"], "works": [{"t": "Selections (unspecified)", "c": null, "w": "104450"}]}, {"id": "36438", "date": "2000-10-26", "label": "Carnegie Hall Jazz Band", "venue": "Isaac Stern Auditorium / Ronald O. Perelman Stage", "roles": ["tenor"], "works": [{"t": "You're Lucky to Me", "c": "Eubie Blake", "w": "106909"}, {"t": "Guess Who's In Town", "c": "J. C. Johnson", "w": "106910"}]}, {"id": "38430", "date": "2002-12-20", "label": "The New York Pops", "venue": "Isaac Stern Auditorium / Ronald O. Perelman Stage", "roles": ["tenor"], "works": [{"t": "No No Nanette: Tea for Two", "c": "Vincent Youmans", "w": "56254"}, {"t": "You Never Know: At Long Last Love", "c": "Cole Porter", "w": "37752"}, {"t": "Anything Goes: I Get a Kick Out of You", "c": "Cole Porter", "w": "34566"}, {"t": "Love is Here to Stay", "c": "George Gershwin", "w": "43752"}, {"t": "Jubilee: Just One of Those Things", "c": "Cole Porter", "w": "51419"}, {"t": "The Garrick Gaieties: Manhattan", "c": "Richard Rodgers", "w": "44141"}, {"t": "The Christmas Song", "c": "Mel Tormé", "w": "19049"}]}, {"id": "38431", "date": "2002-12-21", "label": "The New York Pops", "venue": "Isaac Stern Auditorium / Ronald O. Perelman Stage", "roles": ["tenor"], "works": [{"t": "Anything Goes: I Get a Kick Out of You", "c": "Cole Porter", "w": "34566"}, {"t": "Love is Here to Stay", "c": "George Gershwin", "w": "43752"}, {"t": "Jubilee: Just One of Those Things", "c": "Cole Porter", "w": "51419"}, {"t": "The Garrick Gaieties: Manhattan", "c": "Richard Rodgers", "w": "44141"}, {"t": "No No Nanette: Tea for Two", "c": "Vincent Youmans", "w": "56254"}, {"t": "You Never Know: At Long Last Love", "c": "Cole Porter", "w": "37752"}, {"t": "The Christmas Song", "c": "Mel Tormé", "w": "19049"}]}], "works_created": [], "quotes": [], "about_quotes": [{"speaker": "Jean Bach", "relation": "friend of", "confidence": 1.0, "evidence": "Bobby Short, who is my oldest friend and I, we were celebrating having known each other for 40 years", "doc_title": "Jean Bach interviewed by Monk Rowe, New York City, New York, October 18, 1995", "collection": "hamilton", "url": "https://litsdigital.hamilton.edu/collections/object/jean-bach-interviewed-monk-rowe-new-york-city-new-york-october-18-1995"}, {"speaker": "Marian McPartland", "relation": "friend of", "confidence": 0.95, "evidence": "Bobby Short always laughs when he hears that... Bobby [Short, the pianist and singer at the Café Carlisle] was very friendly with me... I’m always grateful to him, because he really set me up in that room", "doc_title": "Marian McPartland — Smithsonian Jazz Oral History", "collection": "si", "url": "https://amhistory.si.edu/jazz/McPartland-Marian/McPartland_Marian_Transcript.pdf"}, {"speaker": "Anne Phillips", "relation": "played with", "confidence": 0.95, "evidence": "I played actually opposite Bobby Short in his first gig at the — it wasn’t the Carlyle then it was the Beverly Hotel, and I was the other, the off piano.", "doc_title": "Anne Phillips interviewed by Monk Rowe, via Zoom, February 24, 2025", "collection": "hamilton", "url": "https://litsdigital.hamilton.edu/collections/object/anne-phillips-interviewed-monk-rowe-zoom-february-24-2025"}, {"speaker": "Eddie Bert", "relation": "collaborated with", "confidence": 0.95, "evidence": "I’m at the Carlyle and he added three saxes, two trumpets and a trombone about five years ago. So I do that, among other things.", "doc_title": "Eddie Bert interviewed by Monk Rowe, Danbury, Connecticut, November 20, 2001", "collection": "hamilton", "url": "https://litsdigital.hamilton.edu/collections/object/eddie-bert-interviewed-monk-rowe-danbury-connecticut-november-20-2001"}, {"speaker": "Loren Schoenberg", "relation": "collaborated with", "confidence": 0.95, "evidence": "in 1997 I became Bobby Short’s musical director... I wound up doing a thousand one- hour shows with him.", "doc_title": "Loren Schoenberg interviewed by Monk Rowe, New York City, New York, January 14, 2019", "collection": "hamilton", "url": "https://litsdigital.hamilton.edu/collections/object/loren-schoenberg-interviewed-monk-rowe-new-york-city-new-york-january-14-2019"}, {"speaker": "Jimmy McPartland", "relation": "played with", "confidence": 0.95, "evidence": "And we accompanied him with the band you know, came in on his finales and so forth.", "doc_title": "67848_Jimmy McPartland oral history interview", "collection": "rutgers", "url": "https://rucore.libraries.rutgers.edu/rutgers-lib/67848/"}]}