{"qid": "Q993119", "name": "Bruno Carr", "match_basis": "qid", "ch_id": "119951", "ch_uri": "http://data.carnegiehall.org/names/119951", "birth": "1928", "death": "1993", "description": "American musician (1928–1993)", "abstract": "Edward \"Bruno\" Carr (February 9, 1928 – October 25, 1993) was an American jazz drummer. Carr was a frequent collaborator with Ray Charles, and he recorded with Aretha Franklin.", "wp_title": "Bruno Carr", "image": null, "is_interviewee": false, "lj_docs": 1, "lj_mentions": 1, "lj_node": "wd:Q993119", "interviews": [], "concerts": [{"id": "10749", "date": "1975-07-02", "label": "Newport Jazz Festival: Stanley Turrentine, John Klemmer, and Hampton Hawes", "venue": "Main Hall", "roles": ["drums"], "works": [{"t": "Sugar", "c": "Stanley Turrentine", "w": "73543"}, {"t": "Naked as the Day I Was Born", "c": "Billy Page", "w": "107077"}, {"t": "I'm in Love", "c": "Bobby Womack", "w": "107078"}, {"t": "Don't Mess With Mister T.", "c": "Marvin Gaye", "w": "107079"}, {"t": "I Know It's You", "c": "Leon Ware", "w": "107076"}, {"t": "Pieces of Dreams", "c": "Michel Legrand", "w": "54274"}]}], "works_created": [], "quotes": [], "about_quotes": [{"speaker": "Jimmy Owens", "relation": "in music group with", "confidence": 0.95, "evidence": "Bruno Carr, who’s from the Bronx originally, played drums. ... So, it was a good band, you know?", "doc_title": "Jimmy Owens — Smithsonian Jazz Oral History", "collection": "si", "url": "https://amhistory.si.edu/jazz/Owens-Jimmy/Owens_Jimmy_Transcript.pdf"}]}